k7eel/__init__.py
k7eel/main.py
nukeport-0.1.1.dist-info/METADATA
nukeport-0.1.1.dist-info/WHEEL
nukeport-0.1.1.dist-info/entry_points.txt
nukeport-0.1.1.dist-info/top_level.txt
nukeport-0.1.1.dist-info/RECORD
